Workbook

Sheet Suivi trésorerie
A1: 💰 SUIVI DE TRÉSORERIE PRÉVISIONNELLE — VALORCIA · LUCA CRÉATIONS · 123 SPA — 62 semaines
A2: Légende sociétés → | C2: ● Valorcia | F2: ● Luca Créations | I2: ● 123 SPA
A4: 🟢 SECTION ENTRÉES — Argent qui rentre (factures clients, acomptes…)
A5: Société | B5: Nom / client | C5: Prévi (€) | D5: TTC (€) | E5: Reste à facturer | F5: Marge Contrib (€) | G5: Statut | H5: S43 | I5: S44 | J5: S45 | K5: S46 | L5: S47 | M5: S48 | N5: S49 | O5: S50 | P5: S51 | Q5: S52 | R5: S01 | S5: S02 | T5: S03 | U5: S04 | V5: S05 | W5: S06 | X5: S07 | Y5: S08 | Z5: S09 | AA5: S10 | AB5: S11 | AC5: S12 | AD5: S13 | AE5: S14 | AF5: S15 | AG5: S16 | AH5: S17 | AI5: S18 | AJ5: S19 | AK5: S20 | AL5: S21 | AM5: S22 | AN5: S23 | AO5: S24 | AP5: S25 | AQ5: S26 | AR5: S27 | AS5: S28 | AT5: S29 | AU5: S30 | AV5: S31 | AW5: S32 | AX5: S33 | AY5: S34 | AZ5: S35 | BA5: S36 | BB5: S37 | BC5: S38 | BD5: S39 | BE5: S40 | BF5: S41 | BG5: S42 | BH5: S43 | BI5: S44 | BJ5: S45 | BK5: S46 | BL5: S47 | BM5: S48 | BN5: S49 | BO5: S50 | BP5: S51 | BQ5: S52
A6: Valorcia | B6: Broyer | D6: 89300 | E6: 89300 | F6: 40474.786
A7: Valorcia | B7: Poulain | D7: 60000 | E7: 60000 | F7: 13782.051 | L7: 18000 | AD7: 7000 | AH7: 18500 | AZ7: 6500 | BL7: 18000
A8: Valorcia | B8: Sow | D8: 67360 | E8: 30256 | F8: 13059.829 | K8: 18432 | BK8: 18432
A9: Luca Créations | B9: Voz | D9: 38000 | E9: 15909 | F9: 3609 | K9: 9909 | R9: 6000 | AS9: 7400 | BK9: 9909
A10: Valorcia | B10: Sogeca | D10: 41057 | E10: 8330 | F10: 7119.6581 | J10: 10000 | N10: 9500 | AL10: 8000 | BJ10: 10000 | BN10: 9500
A11: Luca Créations | B11: Abate | D11: 37623 | E11: 24814 | F11: 6507.438 | AP11: 4442 | AV11: 17000
A12: Valorcia | B12: Mosca | D12: 72042 | E12: 50430 | F12: 13252.564 | AV12: 16218
A13: Valorcia | B13: Pinto | D13: 50000 | E13: 50000 | F13: 20235.043 | AP13: 16000 | AV13: 18856
A14: Luca Créations | B14: Meyer | D14: 41716 | E14: 24162 | F14: 9438.595 | X14: 12000 | AV14: 7000
A15: 123 SPA | B15: Jager | D15: 27000 | E15: 9741 | F15: 5741 | Q15: 9500 | AC15: 8000 | BQ15: 9500
A16: 123 SPA | B16: casel | D16: 28788 | E16: 18349 | F16: 8690.8333 | R16: 9500 | AL16: 9800 | AS16: 2300
A17: Luca Créations | B17: Pierson | D17: 41258 | E17: 27115 | F17: 12615
A18: 123 SPA | B18: Valleroy | D18: 73800 | E18: 59778 | F18: 26915 | N18: 14200 | BN18: 14200
A19: Luca Créations | B19: Stalens
A20: Valorcia | B20: de sousa
A21: Valorcia | B21: Kuc | D21: 45406 | E21: 45406 | F21: 19808.547 | X21: 13500 | AT21: 11452
A22: Valorcia | B22: Pinheiro | D22: 56000 | E22: 56000 | AC22: 16800 | AI22: 8500 | AW22: 11000
A23: Luca Créations | B23: Schroeder | AG23: 9700
A24: Luca Créations | B24: Brettnacher
A25: Valorcia | B25: Macedo | D25: 40952 | E25: 17542 | F25: 1693.1624 | J25: 12200 | Q25: 11000 | AN25: 9900 | AX25: 7000 | BA25: 1600 | BJ25: 12200 | BQ25: 11000
A26: Valorcia | B26: casagrende | D26: 35204 | E26: 24642.75 | F26: 12288.889 | V26: 10561.25
B27: Vanholder | C27: 109750
A28: 123 SPA | B28: verni | D28: 33645 | E28: 23551.5 | F28: 20537.5 | J28: 10000 | AC28: 10000 | AL28: 8000 | BJ28: 10000
A29: 123 SPA | B29: Nicolas | D29: 39000 | E29: 27300 | F29: 8750 | K29: 11400 | AC29: 5000 | BK29: 11400
A30: Valorcia | B30: retter | T30: 8075
A31: Valorcia | B31: harlange | D31: 47012 | E31: 32908.4 | F31: 16781.197 | V31: 14000 | AS31: 12000
A32: Luca Créations | B32: alan dav | D32: 41150 | E32: 28805 | F32: 8405.7851 | T32: 12300 | AL32: 13000 | AW32: 18500
A33: Luca Créations | B33: Massard | D33: 39207 | E33: 27445 | F33: 10781.818 | T33: 11760 | X33: 9000 | AP33: 13000 | AT33: 6000
A34: Luca Créations | B34: Johan | D34: 6000 | E34: 6000 | F34: 5000
B35: AQUILUX | AX35: 4000
B36: Internationnal pool | AX36: 3500
A37: Luca Créations | B37: Le boulangé | D37: 15252 | E37: 10676.4 | F37: 7654.9587 | AP37: 9000 | AT37: 3000
A38: 123 SPA | B38: Lavigne | D38: 7716 | E38: 5401.2 | F38: 4080 | AT38: 4576
A39: Luca Créations | B39: Saddi | C39: 42000
A40: Valorcia | B40: Moricano
A41: Luca Créations | B41: Claude | C41: 140000
A42: Luca Créations | B42: Maboge | D42: 18000 | E42: 22000 | Y42: 18000
A43: 123 SPA | B43: Graeslin | D43: 19716 | AA43: 5000 | AP43: 2500 | AS43: 13000
A44: Valorcia | B44: Bornet | C44: 60000
A45: Luca Créations | B45: Richard | C45: 82000
A46: Luca Créations | B46: koeck
A47: Valorcia | B47: Antonio | C47: 98000
A48: Valorcia | B48: Kaiser | D48: 53000 | AF48: 16100
A49: Valorcia | B49: Vicky | D49: 61000 | AI49: 18500 | AV49: 21144
A50: Valorcia | B50: Rollinger
A51: 123 SPA | B51: thorner
A52: Luca Créations | B52: forny | D52: 68612 | AH52: 27444.8 | AW52: 11500
A53: Luca Créations | B53: racelle | C53: 60000
A54: Luca Créations | B54: François | D54: 39000 | AH54: 11700
A55: Luca Créations | B55: Fabbri | C55: 70000
A56: Valorcia | B56: reis | C56: 92000 | D56: 36800 | AX56: 36800
A57: Valorcia | B57: alphahome | C57: 55000 | D57: 22000
A58: Luca Créations | B58: dufour | C58: 55000
A59: Luca Créations | B59: h.nicolas | C59: 62000 | D59: 24800 | AP59: 12000 | AY59: 12000
A60: Valorcia | B60: Williams | C60: 70000 | D60: 28000 | AO60: 6000
A61: Valorcia | B61: Schmit | C61: 16000 | D61: 6400 | AP61: 4000 | AU61: 2087
A62: Luca Créations | B62: Renconnet | C62: 11000 | D62: 4400 | AY62: -4000
A63: Valorcia | B63: Jung | C63: 70000 | D63: 28000
A64: Valorcia | B64: Kim keiser | C64: 78000 | D64: 31200
A65: Valorcia | B65: Unica | C65: 94000
B66: Ham
B67: Pierucci
A68: Valorcia | B68: Grun
A69: Luca Créations | B69: Fabbro
A70: 123 SPA | B70: gina belis | C70: 45000
A71: Luca Créations | B71: Dellal
A72: Luca Créations | B72: Blommeart
A73: Valorcia | B73: Castel | C73: 95000
A74: Valorcia | B74: Elvange | C74: 50000
A75: Valorcia | B75: Fievez | C75: 170000
A76: Valorcia | B76: bettigliano | C76: 70000
A77: Luca Créations | B77: domtil | C77: 86000
A78: Valorcia | B78: savini | C78: 132000 | AZ78: 26000
A79: Valorcia | B79: Betti | C79: 47000
A80: Valorcia | B80: Barthel
A81: Luca Créations | B81: Lapraille | C81: 81000
A82: Valorcia | B82: Angelo | C82: 78000
A83: Valorcia | B83: Alvot | C83: 86000
A84: 123 SPA | B84: Loïc Päysagiste
B85: Storckenfeld
B86: Amorosi
A97: ▸ Total ENTRÉES — VALORCIA | H97: =SUMIF($A$6:$A$96,"Valorcia",H6:H96) | I97: =SUMIF($A$6:$A$96,"Valorcia",I6:I96) | J97: =SUMIF($A$6:$A$96,"Valorcia",J6:J96) | K97: =SUMIF($A$6:$A$96,"Valorcia",K6:K96) | L97: =SUMIF($A$6:$A$96,"Valorcia",L6:L96) | M97: =SUMIF($A$6:$A$96,"Valorcia",M6:M96) | N97: =SUMIF($A$6:$A$96,"Valorcia",N6:N96) | O97: =SUMIF($A$6:$A$96,"Valorcia",O6:O96) | ... BQ97: =SUMIF($A$6:$A$96,"Valorcia",BQ6:BQ96)
A98: ▸ Total ENTRÉES — LUCA CRÉATIONS | H98: =SUMIF($A$6:$A$96,"Luca Créations",H6:H96) | I98: =SUMIF($A$6:$A$96,"Luca Créations",I6:I96) | J98: =SUMIF($A$6:$A$96,"Luca Créations",J6:J96) | K98: =SUMIF($A$6:$A$96,"Luca Créations",K6:K96) | L98: =SUMIF($A$6:$A$96,"Luca Créations",L6:L96) | M98: =SUMIF($A$6:$A$96,"Luca Créations",M6:M96) | N98: =SUMIF($A$6:$A$96,"Luca Créations",N6:N96) | O98: =SUMIF($A$6:$A$96,"Luca Créations",O6:O96) | ... BQ98: =SUMIF($A$6:$A$96,"Luca Créations",BQ6:BQ96)
A99: ▸ Total ENTRÉES — 123 SPA | H99: =SUMIF($A$6:$A$96,"123 SPA",H6:H96) | I99: =SUMIF($A$6:$A$96,"123 SPA",I6:I96) | J99: =SUMIF($A$6:$A$96,"123 SPA",J6:J96) | K99: =SUMIF($A$6:$A$96,"123 SPA",K6:K96) | L99: =SUMIF($A$6:$A$96,"123 SPA",L6:L96) | M99: =SUMIF($A$6:$A$96,"123 SPA",M6:M96) | N99: =SUMIF($A$6:$A$96,"123 SPA",N6:N96) | O99: =SUMIF($A$6:$A$96,"123 SPA",O6:O96) | ... BQ99: =SUMIF($A$6:$A$96,"123 SPA",BQ6:BQ96)
A100: 🌍 TOTAL ENTRÉES CONSOLIDÉ | H100: =SUM(H6:H96) | I100: =SUM(I6:I96) | J100: =SUM(J6:J96) | K100: =SUM(K6:K96) | L100: =SUM(L6:L96) | M100: =SUM(M6:M96) | N100: =SUM(N6:N96) | O100: =SUM(O6:O96) | ... BQ100: =SUM(BQ6:BQ96)
A101: 💎 TOTAL MARGE CONTRIB. CONSOLIDÉE | F101: =SUM(F6:F96)
A103: 🔴 SECTION SORTIES — Argent qui sort (achats, loyers, salaires, charges…)
A104: Société | B104: Nom / dépense | G104: Statut | H104: S43 | I104: S44 | J104: S45 | K104: S46 | L104: S47 | M104: S48 | N104: S49 | O104: S50 | P104: S51 | Q104: S52 | R104: S01 | S104: S02 | T104: S03 | U104: S04 | V104: S05 | W104: S06 | X104: S07 | Y104: S08 | Z104: S09 | AA104: S10 | AB104: S11 | AC104: S12 | AD104: S13 | AE104: S14 | AF104: S15 | AG104: S16 | AH104: S17 | AI104: S18 | AJ104: S19 | AK104: S20 | AL104: S21 | AM104: S22 | AN104: S23 | AO104: S24 | AP104: S25 | AQ104: S26 | AR104: S27 | AS104: S28 | AT104: S29 | AU104: S30 | AV104: S31 | AW104: S32 | AX104: S33 | AY104: S34 | AZ104: S35 | BA104: S36 | BB104: S37 | BC104: S38 | BD104: S39 | BE104: S40 | BF104: S41 | BG104: S42 | BH104: S43 | BI104: S44 | BJ104: S45 | BK104: S46 | BL104: S47 | BM104: S48 | BN104: S49 | BO104: S50 | BP104: S51 | BQ104: S52
A105: 123 SPA | B105: Mequisa | J105: 5502.12 | BJ105: 5502.12
A106: Valorcia | B106: Letzhome | L106: 5000 | T106: 6000 | V106: 10500 | X106: 4900 | Y106: 8000 | AH106: 6000 | AL106: 5000 | AO106: 6000 | AS106: 6800 | BL106: 5000
A107: Luca Créations | B107: Magiline | I107: 9500 | N107: 15000 | U107: 15000 | Z107: 10000 | AH107: 22700 | AP107: 9000 | BI107: 9500 | BN107: 15000
A108: Luca Créations | B108: Abris abate | Z108: 6200 | AX108: 6200
A109: Luca Créations | B109: Clément | J109: 550 | AA109: 750 | AB109: 850 | BJ109: 550
A110: 123 SPA | B110: unibeo | J110: 5200 | BJ110: 5200
A111: Valorcia | B111: Angela | AB111: 30000
A112: Valorcia | B112: Yannick | V112: 3000 | AS112: 6700
...

Sheet 📈 Évolution
A1: 📈 ÉVOLUTION DU SOLDE — GLOBAL & PAR SOCIÉTÉ SUR 62 SEMAINES
A3: Semaine | B3: Entrées (€) | C3: Sorties (€) | D3: Diff. hebdo (€) | E3: Cumul global (€) | F3: Cumul Valorcia | G3: Cumul Luca | H3: Cumul 123 SPA
A4: S43 | B4: ='Suivi trésorerie'!H100 | C4: ='Suivi trésorerie'!H160 | D4: ='Suivi trésorerie'!H166 | E4: ='Suivi trésorerie'!H167 | F4: ='Suivi trésorerie'!H168 | G4: ='Suivi trésorerie'!H169 | H4: ='Suivi trésorerie'!H170
A5: S44 | B5: ='Suivi trésorerie'!I100 | C5: ='Suivi trésorerie'!I160 | D5: ='Suivi trésorerie'!I166 | E5: ='Suivi trésorerie'!I167 | F5: ='Suivi trésorerie'!I168 | G5: ='Suivi trésorerie'!I169 | H5: ='Suivi trésorerie'!I170
A6: S45 | B6: ='Suivi trésorerie'!J100 | C6: ='Suivi trésorerie'!J160 | D6: ='Suivi trésorerie'!J166 | E6: ='Suivi trésorerie'!J167 | F6: ='Suivi trésorerie'!J168 | G6: ='Suivi trésorerie'!J169 | H6: ='Suivi trésorerie'!J170
A7: S46 | B7: ='Suivi trésorerie'!K100 | C7: ='Suivi trésorerie'!K160 | D7: ='Suivi trésorerie'!K166 | E7: ='Suivi trésorerie'!K167 | F7: ='Suivi trésorerie'!K168 | G7: ='Suivi trésorerie'!K169 | H7: ='Suivi trésorerie'!K170
A8: S47 | B8: ='Suivi trésorerie'!L100 | C8: ='Suivi trésorerie'!L160 | D8: ='Suivi trésorerie'!L166 | E8: ='Suivi trésorerie'!L167 | F8: ='Suivi trésorerie'!L168 | G8: ='Suivi trésorerie'!L169 | H8: ='Suivi trésorerie'!L170
A9: S48 | B9: ='Suivi trésorerie'!M100 | C9: ='Suivi trésorerie'!M160 | D9: ='Suivi trésorerie'!M166 | E9: ='Suivi trésorerie'!M167 | F9: ='Suivi trésorerie'!M168 | G9: ='Suivi trésorerie'!M169 | H9: ='Suivi trésorerie'!M170
A10: S49 | B10: ='Suivi trésorerie'!N100 | C10: ='Suivi trésorerie'!N160 | D10: ='Suivi trésorerie'!N166 | E10: ='Suivi trésorerie'!N167 | F10: ='Suivi trésorerie'!N168 | G10: ='Suivi trésorerie'!N169 | H10: ='Suivi trésorerie'!N170
A11: S50 | B11: ='Suivi trésorerie'!O100 | C11: ='Suivi trésorerie'!O160 | D11: ='Suivi trésorerie'!O166 | E11: ='Suivi trésorerie'!O167 | F11: ='Suivi trésorerie'!O168 | G11: ='Suivi trésorerie'!O169 | H11: ='Suivi trésorerie'!O170
A12: S51 | B12: ='Suivi trésorerie'!P100 | C12: ='Suivi trésorerie'!P160 | D12: ='Suivi trésorerie'!P166 | E12: ='Suivi trésorerie'!P167 | F12: ='Suivi trésorerie'!P168 | G12: ='Suivi trésorerie'!P169 | H12: ='Suivi trésorerie'!P170
A13: S52 | B13: ='Suivi trésorerie'!Q100 | C13: ='Suivi trésorerie'!Q160 | D13: ='Suivi trésorerie'!Q166 | E13: ='Suivi trésorerie'!Q167 | F13: ='Suivi trésorerie'!Q168 | G13: ='Suivi trésorerie'!Q169 | H13: ='Suivi trésorerie'!Q170
A14: S01 | B14: ='Suivi trésorerie'!R100 | C14: ='Suivi trésorerie'!R160 | D14: ='Suivi trésorerie'!R166 | E14: ='Suivi trésorerie'!R167 | F14: ='Suivi trésorerie'!R168 | G14: ='Suivi trésorerie'!R169 | H14: ='Suivi trésorerie'!R170
A15: S02 | B15: ='Suivi trésorerie'!S100 | C15: ='Suivi trésorerie'!S160 | D15: ='Suivi trésorerie'!S166 | E15: ='Suivi trésorerie'!S167 | F15: ='Suivi trésorerie'!S168 | G15: ='Suivi trésorerie'!S169 | H15: ='Suivi trésorerie'!S170
A16: S03 | B16: ='Suivi trésorerie'!T100 | C16: ='Suivi trésorerie'!T160 | D16: ='Suivi trésorerie'!T166 | E16: ='Suivi trésorerie'!T167 | F16: ='Suivi trésorerie'!T168 | G16: ='Suivi trésorerie'!T169 | H16: ='Suivi trésorerie'!T170
A17: S04 | B17: ='Suivi trésorerie'!U100 | C17: ='Suivi trésorerie'!U160 | D17: ='Suivi trésorerie'!U166 | E17: ='Suivi trésorerie'!U167 | F17: ='Suivi trésorerie'!U168 | G17: ='Suivi trésorerie'!U169 | H17: ='Suivi trésorerie'!U170
A18: S05 | B18: ='Suivi trésorerie'!V100 | C18: ='Suivi trésorerie'!V160 | D18: ='Suivi trésorerie'!V166 | E18: ='Suivi trésorerie'!V167 | F18: ='Suivi trésorerie'!V168 | G18: ='Suivi trésorerie'!V169 | H18: ='Suivi trésorerie'!V170
A19: S06 | B19: ='Suivi trésorerie'!W100 | C19: ='Suivi trésorerie'!W160 | D19: ='Suivi trésorerie'!W166 | E19: ='Suivi trésorerie'!W167 | F19: ='Suivi trésorerie'!W168 | G19: ='Suivi trésorerie'!W169 | H19: ='Suivi trésorerie'!W170
A20: S07 | B20: ='Suivi trésorerie'!X100 | C20: ='Suivi trésorerie'!X160 | D20: ='Suivi trésorerie'!X166 | E20: ='Suivi trésorerie'!X167 | F20: ='Suivi trésorerie'!X168 | G20: ='Suivi trésorerie'!X169 | H20: ='Suivi trésorerie'!X170
A21: S08 | B21: ='Suivi trésorerie'!Y100 | C21: ='Suivi trésorerie'!Y160 | D21: ='Suivi trésorerie'!Y166 | E21: ='Suivi trésorerie'!Y167 | F21: ='Suivi trésorerie'!Y168 | G21: ='Suivi trésorerie'!Y169 | H21: ='Suivi trésorerie'!Y170
A22: S09 | B22: ='Suivi trésorerie'!Z100 | C22: ='Suivi trésorerie'!Z160 | D22: ='Suivi trésorerie'!Z166 | E22: ='Suivi trésorerie'!Z167 | F22: ='Suivi trésorerie'!Z168 | G22: ='Suivi trésorerie'!Z169 | H22: ='Suivi trésorerie'!Z170
A23: S10 | B23: ='Suivi trésorerie'!AA100 | C23: ='Suivi trésorerie'!AA160 | D23: ='Suivi trésorerie'!AA166 | E23: ='Suivi trésorerie'!AA167 | F23: ='Suivi trésorerie'!AA168 | G23: ='Suivi trésorerie'!AA169 | H23: ='Suivi trésorerie'!AA170
A24: S11 | B24: ='Suivi trésorerie'!AB100 | C24: ='Suivi trésorerie'!AB160 | D24: ='Suivi trésorerie'!AB166 | E24: ='Suivi trésorerie'!AB167 | F24: ='Suivi trésorerie'!AB168 | G24: ='Suivi trésorerie'!AB169 | H24: ='Suivi trésorerie'!AB170
A25: S12 | B25: ='Suivi trésorerie'!AC100 | C25: ='Suivi trésorerie'!AC160 | D25: ='Suivi trésorerie'!AC166 | E25: ='Suivi trésorerie'!AC167 | F25: ='Suivi trésorerie'!AC168 | G25: ='Suivi trésorerie'!AC169 | H25: ='Suivi trésorerie'!AC170
A26: S13 | B26: ='Suivi trésorerie'!AD100 | C26: ='Suivi trésorerie'!AD160 | D26: ='Suivi trésorerie'!AD166 | E26: ='Suivi trésorerie'!AD167 | F26: ='Suivi trésorerie'!AD168 | G26: ='Suivi trésorerie'!AD169 | H26: ='Suivi trésorerie'!AD170
A27: S14 | B27: ='Suivi trésorerie'!AE100 | C27: ='Suivi trésorerie'!AE160 | D27: ='Suivi trésorerie'!AE166 | E27: ='Suivi trésorerie'!AE167 | F27: ='Suivi trésorerie'!AE168 | G27: ='Suivi trésorerie'!AE169 | H27: ='Suivi trésorerie'!AE170
A28: S15 | B28: ='Suivi trésorerie'!AF100 | C28: ='Suivi trésorerie'!AF160 | D28: ='Suivi trésorerie'!AF166 | E28: ='Suivi trésorerie'!AF167 | F28: ='Suivi trésorerie'!AF168 | G28: ='Suivi trésorerie'!AF169 | H28: ='Suivi trésorerie'!AF170
A29: S16 | B29: ='Suivi trésorerie'!AG100 | C29: ='Suivi trésorerie'!AG160 | D29: ='Suivi trésorerie'!AG166 | E29: ='Suivi trésorerie'!AG167 | F29: ='Suivi trésorerie'!AG168 | G29: ='Suivi trésorerie'!AG169 | H29: ='Suivi trésorerie'!AG170
A30: S17 | B30: ='Suivi trésorerie'!AH100 | C30: ='Suivi trésorerie'!AH160 | D30: ='Suivi trésorerie'!AH166 | E30: ='Suivi trésorerie'!AH167 | F30: ='Suivi trésorerie'!AH168 | G30: ='Suivi trésorerie'!AH169 | H30: ='Suivi trésorerie'!AH170
A31: S18 | B31: ='Suivi trésorerie'!AI100 | C31: ='Suivi trésorerie'!AI160 | D31: ='Suivi trésorerie'!AI166 | E31: ='Suivi trésorerie'!AI167 | F31: ='Suivi trésorerie'!AI168 | G31: ='Suivi trésorerie'!AI169 | H31: ='Suivi trésorerie'!AI170
A32: S19 | B32: ='Suivi trésorerie'!AJ100 | C32: ='Suivi trésorerie'!AJ160 | D32: ='Suivi trésorerie'!AJ166 | E32: ='Suivi trésorerie'!AJ167 | F32: ='Suivi trésorerie'!AJ168 | G32: ='Suivi trésorerie'!AJ169 | H32: ='Suivi trésorerie'!AJ170
A33: S20 | B33: ='Suivi trésorerie'!AK100 | C33: ='Suivi trésorerie'!AK160 | D33: ='Suivi trésorerie'!AK166 | E33: ='Suivi trésorerie'!AK167 | F33: ='Suivi trésorerie'!AK168 | G33: ='Suivi trésorerie'!AK169 | H33: ='Suivi trésorerie'!AK170
A34: S21 | B34: ='Suivi trésorerie'!AL100 | C34: ='Suivi trésorerie'!AL160 | D34: ='Suivi trésorerie'!AL166 | E34: ='Suivi trésorerie'!AL167 | F34: ='Suivi trésorerie'!AL168 | G34: ='Suivi trésorerie'!AL169 | H34: ='Suivi trésorerie'!AL170
A35: S22 | B35: ='Suivi trésorerie'!AM100 | C35: ='Suivi trésorerie'!AM160 | D35: ='Suivi trésorerie'!AM166 | E35: ='Suivi trésorerie'!AM167 | F35: ='Suivi trésorerie'!AM168 | G35: ='Suivi trésorerie'!AM169 | H35: ='Suivi trésorerie'!AM170
A36: S23 | B36: ='Suivi trésorerie'!AN100 | C36: ='Suivi trésorerie'!AN160 | D36: ='Suivi trésorerie'!AN166 | E36: ='Suivi trésorerie'!AN167 | F36: ='Suivi trésorerie'!AN168 | G36: ='Suivi trésorerie'!AN169 | H36: ='Suivi trésorerie'!AN170
A37: S24 | B37: ='Suivi trésorerie'!AO100 | C37: ='Suivi trésorerie'!AO160 | D37: ='Suivi trésorerie'!AO166 | E37: ='Suivi trésorerie'!AO167 | F37: ='Suivi trésorerie'!AO168 | G37: ='Suivi trésorerie'!AO169 | H37: ='Suivi trésorerie'!AO170
A38: S25 | B38: ='Suivi trésorerie'!AP100 | C38: ='Suivi trésorerie'!AP160 | D38: ='Suivi trésorerie'!AP166 | E38: ='Suivi trésorerie'!AP167 | F38: ='Suivi trésorerie'!AP168 | G38: ='Suivi trésorerie'!AP169 | H38: ='Suivi trésorerie'!AP170
A39: S26 | B39: ='Suivi trésorerie'!AQ100 | C39: ='Suivi trésorerie'!AQ160 | D39: ='Suivi trésorerie'!AQ166 | E39: ='Suivi trésorerie'!AQ167 | F39: ='Suivi trésorerie'!AQ168 | G39: ='Suivi trésorerie'!AQ169 | H39: ='Suivi trésorerie'!AQ170
A40: S27 | B40: ='Suivi trésorerie'!AR100 | C40: ='Suivi trésorerie'!AR160 | D40: ='Suivi trésorerie'!AR166 | E40: ='Suivi trésorerie'!AR167 | F40: ='Suivi trésorerie'!AR168 | G40: ='Suivi trésorerie'!AR169 | H40: ='Suivi trésorerie'!AR170
A41: S28 | B41: ='Suivi trésorerie'!AS100 | C41: ='Suivi trésorerie'!AS160 | D41: ='Suivi trésorerie'!AS166 | E41: ='Suivi trésorerie'!AS167 | F41: ='Suivi trésorerie'!AS168 | G41: ='Suivi trésorerie'!AS169 | H41: ='Suivi trésorerie'!AS170
A42: S29 | B42: ='Suivi trésorerie'!AT100 | C42: ='Suivi trésorerie'!AT160 | D42: ='Suivi trésorerie'!AT166 | E42: ='Suivi trésorerie'!AT167 | F42: ='Suivi trésorerie'!AT168 | G42: ='Suivi trésorerie'!AT169 | H42: ='Suivi trésorerie'!AT170
A43: S30 | B43: ='Suivi trésorerie'!AU100 | C43: ='Suivi trésorerie'!AU160 | D43: ='Suivi trésorerie'!AU166 | E43: ='Suivi trésorerie'!AU167 | F43: ='Suivi trésorerie'!AU168 | G43: ='Suivi trésorerie'!AU169 | H43: ='Suivi trésorerie'!AU170
A44: S31 | B44: ='Suivi trésorerie'!AV100 | C44: ='Suivi trésorerie'!AV160 | D44: ='Suivi trésorerie'!AV166 | E44: ='Suivi trésorerie'!AV167 | F44: ='Suivi trésorerie'!AV168 | G44: ='Suivi trésorerie'!AV169 | H44: ='Suivi trésorerie'!AV170
A45: S32 | B45: ='Suivi trésorerie'!AW100 | C45: ='Suivi trésorerie'!AW160 | D45: ='Suivi trésorerie'!AW166 | E45: ='Suivi trésorerie'!AW167 | F45: ='Suivi trésorerie'!AW168 | G45: ='Suivi trésorerie'!AW169 | H45: ='Suivi trésorerie'!AW170
A46: S33 | B46: ='Suivi trésorerie'!AX100 | C46: ='Suivi trésorerie'!AX160 | D46: ='Suivi trésorerie'!AX166 | E46: ='Suivi trésorerie'!AX167 | F46: ='Suivi trésorerie'!AX168 | G46: ='Suivi trésorerie'!AX169 | H46: ='Suivi trésorerie'!AX170
A47: S34 | B47: ='Suivi trésorerie'!AY100 | C47: ='Suivi trésorerie'!AY160 | D47: ='Suivi trésorerie'!AY166 | E47: ='Suivi trésorerie'!AY167 | F47: ='Suivi trésorerie'!AY168 | G47: ='Suivi trésorerie'!AY169 | H47: ='Suivi trésorerie'!AY170
A48: S35 | B48: ='Suivi trésorerie'!AZ100 | C48: ='Suivi trésorerie'!AZ160 | D48: ='Suivi trésorerie'!AZ166 | E48: ='Suivi trésorerie'!AZ167 | F48: ='Suivi trésorerie'!AZ168 | G48: ='Suivi trésorerie'!AZ169 | H48: ='Suivi trésorerie'!AZ170
A49: S36 | B49: ='Suivi trésorerie'!BA100 | C49: ='Suivi trésorerie'!BA160 | D49: ='Suivi trésorerie'!BA166 | E49: ='Suivi trésorerie'!BA167 | F49: ='Suivi trésorerie'!BA168 | G49: ='Suivi trésorerie'!BA169 | H49: ='Suivi trésorerie'!BA170
A50: S37 | B50: ='Suivi trésorerie'!BB100 | C50: ='Suivi trésorerie'!BB160 | D50: ='Suivi trésorerie'!BB166 | E50: ='Suivi trésorerie'!BB167 | F50: ='Suivi trésorerie'!BB168 | G50: ='Suivi trésorerie'!BB169 | H50: ='Suivi trésorerie'!BB170
A51: S38 | B51: ='Suivi trésorerie'!BC100 | C51: ='Suivi trésorerie'!BC160 | D51: ='Suivi trésorerie'!BC166 | E51: ='Suivi trésorerie'!BC167 | F51: ='Suivi trésorerie'!BC168 | G51: ='Suivi trésorerie'!BC169 | H51: ='Suivi trésorerie'!BC170
A52: S39 | B52: ='Suivi trésorerie'!BD100 | C52: ='Suivi trésorerie'!BD160 | D52: ='Suivi trésorerie'!BD166 | E52: ='Suivi trésorerie'!BD167 | F52: ='Suivi trésorerie'!BD168 | G52: ='Suivi trésorerie'!BD169 | H52: ='Suivi trésorerie'!BD170
A53: S40 | B53: ='Suivi trésorerie'!BE100 | C53: ='Suivi trésorerie'!BE160 | D53: ='Suivi trésorerie'!BE166 | E53: ='Suivi trésorerie'!BE167 | F53: ='Suivi trésorerie'!BE168 | G53: ='Suivi trésorerie'!BE169 | H53: ='Suivi trésorerie'!BE170
A54: S41 | B54: ='Suivi trésorerie'!BF100 | C54: ='Suivi trésorerie'!BF160 | D54: ='Suivi trésorerie'!BF166 | E54: ='Suivi trésorerie'!BF167 | F54: ='Suivi trésorerie'!BF168 | G54: ='Suivi trésorerie'!BF169 | H54: ='Suivi trésorerie'!BF170
A55: S42 | B55: ='Suivi trésorerie'!BG100 | C55: ='Suivi trésorerie'!BG160 | D55: ='Suivi trésorerie'!BG166 | E55: ='Suivi trésorerie'!BG167 | F55: ='Suivi trésorerie'!BG168 | G55: ='Suivi trésorerie'!BG169 | H55: ='Suivi trésorerie'!BG170
A56: S43 | B56: ='Suivi trésorerie'!BH100 | C56: ='Suivi trésorerie'!BH160 | D56: ='Suivi trésorerie'!BH166 | E56: ='Suivi trésorerie'!BH167 | F56: ='Suivi trésorerie'!BH168 | G56: ='Suivi trésorerie'!BH169 | H56: ='Suivi trésorerie'!BH170
A57: S44 | B57: ='Suivi trésorerie'!BI100 | C57: ='Suivi trésorerie'!BI160 | D57: ='Suivi trésorerie'!BI166 | E57: ='Suivi trésorerie'!BI167 | F57: ='Suivi trésorerie'!BI168 | G57: ='Suivi trésorerie'!BI169 | H57: ='Suivi trésorerie'!BI170
A58: S45 | B58: ='Suivi trésorerie'!BJ100 | C58: ='Suivi trésorerie'!BJ160 | D58: ='Suivi trésorerie'!BJ166 | E58: ='Suivi trésorerie'!BJ167 | F58: ='Suivi trésorerie'!BJ168 | G58: ='Suivi trésorerie'!BJ169 | H58: ='Suivi trésorerie'!BJ170
A59: S46 | B59: ='Suivi trésorerie'!BK100 | C59: ='Suivi trésorerie'!BK160 | D59: ='Suivi trésorerie'!BK166 | E59: ='Suivi trésorerie'!BK167 | F59: ='Suivi trésorerie'!BK168 | G59: ='Suivi trésorerie'!BK169 | H59: ='Suivi trésorerie'!BK170
A60: S47 | B60: ='Suivi trésorerie'!BL100 | C60: ='Suivi trésorerie'!BL160 | D60: ='Suivi trésorerie'!BL166 | E60: ='Suivi trésorerie'!BL167 | F60: ='Suivi trésorerie'!BL168 | G60: ='Suivi trésorerie'!BL169 | H60: ='Suivi trésorerie'!BL170
A61: S48 | B61: ='Suivi trésorerie'!BM100 | C61: ='Suivi trésorerie'!BM160 | D61: ='Suivi trésorerie'!BM166 | E61: ='Suivi trésorerie'!BM167 | F61: ='Suivi trésorerie'!BM168 | G61: ='Suivi trésorerie'!BM169 | H61: ='Suivi trésorerie'!BM170
A62: S49 | B62: ='Suivi trésorerie'!BN100 | C62: ='Suivi trésorerie'!BN160 | D62: ='Suivi trésorerie'!BN166 | E62: ='Suivi trésorerie'!BN167 | F62: ='Suivi trésorerie'!BN168 | G62: ='Suivi trésorerie'!BN169 | H62: ='Suivi trésorerie'!BN170
A63: S50 | B63: ='Suivi trésorerie'!BO100 | C63: ='Suivi trésorerie'!BO160 | D63: ='Suivi trésorerie'!BO166 | E63: ='Suivi trésorerie'!BO167 | F63: ='Suivi trésorerie'!BO168 | G63: ='Suivi trésorerie'!BO169 | H63: ='Suivi trésorerie'!BO170
A64: S51 | B64: ='Suivi trésorerie'!BP100 | C64: ='Suivi trésorerie'!BP160 | D64: ='Suivi trésorerie'!BP166 | E64: ='Suivi trésorerie'!BP167 | F64: ='Suivi trésorerie'!BP168 | G64: ='Suivi trésorerie'!BP169 | H64: ='Suivi trésorerie'!BP170
A65: S52 | B65: ='Suivi trésorerie'!BQ100 | C65: ='Suivi trésorerie'!BQ160 | D65: ='Suivi trésorerie'!BQ166 | E65: ='Suivi trésorerie'!BQ167 | F65: ='Suivi trésorerie'!BQ168 | G65: ='Suivi trésorerie'!BQ169 | H65: ='Suivi trésorerie'!BQ170

Sheet 🎯 Tableau de bord
A1: 🎯 TABLEAU DE BORD — Vision synthétique
A3: 🌍 INDICATEURS GLOBAUX
A4: Total ENTRÉES prévues (62 sem.) | B4: =SUM('Suivi trésorerie'!H100:BQ100)
A5: Total SORTIES prévues (62 sem.) | B5: =SUM('Suivi trésorerie'!H160:BQ160)
A6: 💎 Total MARGE CONTRIB. prévue | B6: ='Suivi trésorerie'!F101
A7: SOLDE FINAL (fin de période) | B7: ='Suivi trésorerie'!BQ167
A8: Différence moyenne hebdo | B8: =AVERAGE('Suivi trésorerie'!H166:BQ166)
A9: Meilleure semaine | B9: =MAX('Suivi trésorerie'!H166:BQ166)
A10: Pire semaine | B10: =MIN('Suivi trésorerie'!H166:BQ166)
A13: 🏢 INDICATEURS PAR SOCIÉTÉ
A14: Société | B14: Entrées | C14: Sorties | D14: Différence | E14: Statut
A15: Valorcia | B15: =SUM('Suivi trésorerie'!H97:BQ97) | C15: =SUM('Suivi trésorerie'!H157:BQ157) | D15: =B15-C15 | E15: =IF(D15>0,"✅ Positif",IF(D15=0,"⚪ Neutre","🔴 Négatif"))
A16: Luca Créations | B16: =SUM('Suivi trésorerie'!H98:BQ98) | C16: =SUM('Suivi trésorerie'!H158:BQ158) | D16: =B16-C16 | E16: =IF(D16>0,"✅ Positif",IF(D16=0,"⚪ Neutre","🔴 Négatif"))
A17: 123 SPA | B17: =SUM('Suivi trésorerie'!H99:BQ99) | C17: =SUM('Suivi trésorerie'!H159:BQ159) | D17: =B17-C17 | E17: =IF(D17>0,"✅ Positif",IF(D17=0,"⚪ Neutre","🔴 Négatif"))
A20: ⚠️ ALERTES
A21: Nombre de semaines à différence négative | B21: =COUNTIF('Suivi trésorerie'!H166:BQ166,"<0")
A22: Nombre de semaines où le solde cumulé est négatif | B22: =COUNTIF('Suivi trésorerie'!H167:BQ167,"<0")

Sheet 🚨 Impayés
A1: 🚨 SUIVI DES IMPAYÉS & RETARDS
A3: Société | B3: Nom client | C3: Projet | D3: Montant HT (€) | E3: Échéance | F3: Jours retard | G3: Statut | H3: Dernière relance | I3: Actions à mener
F4: =IF(E4="","",TODAY()-E4)
F5: =IF(E5="","",TODAY()-E5)
F6: =IF(E6="","",TODAY()-E6)
F7: =IF(E7="","",TODAY()-E7)
F8: =IF(E8="","",TODAY()-E8)
F9: =IF(E9="","",TODAY()-E9)
F10: =IF(E10="","",TODAY()-E10)
F11: =IF(E11="","",TODAY()-E11)
F12: =IF(E12="","",TODAY()-E12)
F13: =IF(E13="","",TODAY()-E13)
F14: =IF(E14="","",TODAY()-E14)
F15: =IF(E15="","",TODAY()-E15)
... F40: =IF(E40="","",TODAY()-E40)
A43: ▸ Total impayés — VALORCIA | D43: =SUMIF(A4:A40,"Valorcia",D4:D40)
A44: ▸ Total impayés — LUCA CRÉATIONS | D44: =SUMIF(A4:A40,"Luca Créations",D4:D40)
A45: ▸ Total impayés — 123 SPA | D45: =SUMIF(A4:A40,"123 SPA",D4:D40)
A46: 🌍 TOTAL IMPAYÉS CONSOLIDÉ | D46: =SUM(D4:D40)

Sheet 📖 Mode d'emploi
A1: 📖 MODE D'EMPLOI — Suivi trésorerie enrichi v2
A3: 🎯 NOUVEAUTÉS DE CETTE VERSION
A4: ✨ Colonne « Marge Contrib. » ajoutée dans la section entrées (fond jaune)
A5: ✨ Extension à 62 semaines (S43 → S52 de l'année suivante)
A6: ✨ Nouveau graphique : évolution du solde cumulé PAR SOCIÉTÉ (3 courbes)
A8: 🎯 CONTENU DU FICHIER
A9: Reprend toutes les données de votre fichier prévisionnel :
A10: • 62 semaines au total (46 existantes + 16 nouvelles pour planifier)
A11: • 81 lignes d'entrées avec Prévi / TTC / Reste à facturer / MARGE CONTRIB.
A12: • 44 lignes de sorties par société
A13: • Sous-totaux automatiques par société + total consolidé
A15: 📄 FEUILLE 1 : SUIVI TRÉSORERIE
... A46: • Format d'impression : A3 paysage
